aksharamukha/Convert.py
aksharamukha/ConvertFix.py
aksharamukha/FallBack.py
aksharamukha/GeneralMap.py
aksharamukha/PostOptions.py
aksharamukha/PostProcess.py
aksharamukha/PreOptions.py
aksharamukha/PreProcess.py
aksharamukha/__init__.py
aksharamukha/demo.py
aksharamukha/gimeltra.py
aksharamukha/transliterate.py
aksharamukha/transliterate_file.py
aksharamukha/ScriptMap/FallBack.py
aksharamukha/ScriptMap/__init__.py
aksharamukha/ScriptMap/EastIndic/Balinese.py
aksharamukha/ScriptMap/EastIndic/BatakKaro.py
aksharamukha/ScriptMap/EastIndic/BatakManda.py
aksharamukha/ScriptMap/EastIndic/BatakPakpak.py
aksharamukha/ScriptMap/EastIndic/BatakSima.py
aksharamukha/ScriptMap/EastIndic/BatakToba.py
aksharamukha/ScriptMap/EastIndic/Buginese.py
aksharamukha/ScriptMap/EastIndic/Buhid.py
aksharamukha/ScriptMap/EastIndic/Burmese.py
aksharamukha/ScriptMap/EastIndic/Cham.py
aksharamukha/ScriptMap/EastIndic/DivesAkuru.py
aksharamukha/ScriptMap/EastIndic/Hanunoo.py
aksharamukha/ScriptMap/EastIndic/Javanese.py
aksharamukha/ScriptMap/EastIndic/Kawi.py
aksharamukha/ScriptMap/EastIndic/KhamtiShan.py
aksharamukha/ScriptMap/EastIndic/Khmer.py
aksharamukha/ScriptMap/EastIndic/KhmerLoC.py
aksharamukha/ScriptMap/EastIndic/KhomThai.py
aksharamukha/ScriptMap/EastIndic/KhuenTham.py
aksharamukha/ScriptMap/EastIndic/Lao.py
aksharamukha/ScriptMap/EastIndic/Lao2.py
aksharamukha/ScriptMap/EastIndic/LaoPali.py
aksharamukha/ScriptMap/EastIndic/LaoTham.py
aksharamukha/ScriptMap/EastIndic/LueTham.py
aksharamukha/ScriptMap/EastIndic/Makasar.py
aksharamukha/ScriptMap/EastIndic/Marchen.py
aksharamukha/ScriptMap/EastIndic/Mon.py
aksharamukha/ScriptMap/EastIndic/Pallava.py
aksharamukha/ScriptMap/EastIndic/PhagsPa.py
aksharamukha/ScriptMap/EastIndic/Rejang.py
aksharamukha/ScriptMap/EastIndic/Shan.py
aksharamukha/ScriptMap/EastIndic/ShanLoC.py
aksharamukha/ScriptMap/EastIndic/Siddham.py
aksharamukha/ScriptMap/EastIndic/SiddhamRanjana.py
aksharamukha/ScriptMap/EastIndic/Soyombo.py
aksharamukha-2.3.dist-info/METADATA
aksharamukha-2.3.dist-info/WHEEL
aksharamukha-2.3.dist-info/top_level.txt
aksharamukha-2.3.dist-info/RECORD
