Metadata-Version: 2.1
Name: aksharamukha
Version: 2.3
Summary: Provides script conversion (a.k.a transliteration) between various scripts
Home-page: https://github.com/virtualvinodh/aksharamukha-python
Author: Vinodh Rajan
Author-email: vinodh@virtualvindh.com
License: GNU AGPL 3.0
Keywords: unicode semitic arabic syriac hebrew indic indian language script brahmi brahmic asian transliteration conversion writing alphabet romanization
Platform: UNKNOWN
Classifier: Development Status :: 5 - Production/Stable
Classifier: Intended Audience :: Education
Classifier: Intended Audience :: Science/Research
Classifier: Intended Audience :: Developers
Classifier: Natural Language :: Tamil
Classifier: Natural Language :: Telugu
Classifier: Natural Language :: Hindi
Classifier: Natural Language :: Marathi
Classifier: Natural Language :: Bengali
Classifier: Natural Language :: Urdu
Classifier: Natural Language :: Thai
Classifier: Natural Language :: Tibetan
Classifier: Natural Language :: Hebrew
Classifier: Natural Language :: Arabic
Classifier: Topic :: Text Processing :: Linguistic
Classifier: License :: OSI Approved :: GNU Affero General Public License v3
Classifier: Programming Language :: Python :: 3.8
Classifier: Programming Language :: Python :: 3.9
Classifier: Programming Language :: Python :: 3.10
